pyvium/__init__.py
pyvium/core/__init__.py
pyvium/core/constants.py
pyvium/core/core_base.py
pyvium/core/direct_mode_functions.py
pyvium/core/generic_functions.py
pyvium/core/method_mode_functions.py
pyvium/core/we32_functions.py
pyvium/errors/__init__.py
pyvium/errors/cell_off.py
pyvium/errors/device_busy.py
pyvium/errors/device_not_connected_to_iviumsoft.py
pyvium/errors/driver_not_open.py
pyvium/errors/no_device_detected.py
pyvium/errors/no_iviumsoft_running.py
pyvium/IVIUM_remdriver.dll
pyvium/Ivium_remdriver64.dll
pyvium/pyvium/__init__.py
pyvium/pyvium/direct_mode_functions.py
pyvium/pyvium/generic_functions.py
pyvium/pyvium/method_mode_functions.py
pyvium/pyvium_verifiers.py
pyvium/tools/__init__.py
pyvium/tools/data_processing_functions.py
pyvium/util/__init__.py
pyvium/util/get_file_list.py
pyvium/util/get_ivium_dll_path.py
pyvium-0.1.21.dist-info/LICENSE
pyvium-0.1.21.dist-info/METADATA
pyvium-0.1.21.dist-info/WHEEL
pyvium-0.1.21.dist-info/RECORD
