Metadata-Version: 2.3
Name: pyvium
Version: 0.1.21
Summary: A tiny Python wrapper around the <Software development driver DLL> for IviumSoft.
License: Apache-2.0
Keywords: ivium,iviumsoft,ivium software,ivium compactstat
Author: Alejandro Gutiérrez
Author-email: agutierrez@stec.es
Requires-Python: >=3.11,<3.13
Classifier: Development Status :: 4 - Beta
Classifier: Intended Audience :: Developers
Classifier: License :: OSI Approved :: Apache Software License
Classifier: Programming Language :: Python :: 3
Classifier: Programming Language :: Python :: 3.11
Classifier: Programming Language :: Python :: 3.12
Classifier: Programming Language :: Python :: 2
Requires-Dist: cffi (>=1.15.1,<2.0.0)
Requires-Dist: tqdm (>=4.65.0,<5.0.0)
Project-URL: Homepage, https://github.com/SF-Tec/pyvium
Project-URL: Repository, https://github.com/SF-Tec/pyvium
